{
    "coord":{
       "lon":-75.1638,
       "lat":39.9523
    },
    "weather":[
       {
          "id":804,
          "main":"Clouds",
          "description":"overcast clouds",
          "icon":"04d"
       }
    ],
    "base":"stations",
    "main":{
       "temp":302,
       "feels_like":303.79,
       "temp_min":299.66,
       "temp_max":303.81,
       "pressure":1009,
       "humidity":59
    },
    "visibility":10000,
    "wind":{
       "speed":0.89,
       "deg":123,
       "gust":1.79
    },
    "clouds":{
       "all":90
    },
    "dt":1630426143,
    "sys":{
       "type":2,
       "id":2037403,
       "country":"US",
       "sunrise":1630405677,
       "sunset":1630452857
    },
    "timezone":-14400,
    "id":4560349,
    "name":"Philadelphia",
    "cod":200
 }